sqlalchemy_csv_writer/__init__.py
sqlalchemy_csv_writer/writer.py
sqlalchemy_csv_writer-0.4.2.dist-info/LICENSE
sqlalchemy_csv_writer-0.4.2.dist-info/METADATA
sqlalchemy_csv_writer-0.4.2.dist-info/WHEEL
sqlalchemy_csv_writer-0.4.2.dist-info/RECORD
