Metadata-Version: 2.1
Name: sqlalchemy-csv-writer
Version: 0.4.2
Summary: Write SQLAlchemy results to csv files
Home-page: https://raayu83.github.io/sqlalchemy-csv-writer/
Keywords: sqlalchemy,csv
Author: Rayuu83
Author-email: rayuu83@spellweb.de
Requires-Python: >=3.9,<4.0
Classifier: Programming Language :: Python :: 3
Classifier: Programming Language :: Python :: 3.9
Classifier: Programming Language :: Python :: 3.10
Classifier: Programming Language :: Python :: 3.11
Classifier: Programming Language :: Python :: 3.12
Classifier: Topic :: Database :: Front-Ends
Classifier: Topic :: Software Development :: Libraries :: Python Modules
Requires-Dist: sqlalchemy (>=2.0.0)
Project-URL: Repository, https://github.com/raayu83/sqlalchemy-csv-writer
